{
"Language":  {
                 "ES":  {
                            "label":  "Spanish",
                            "code":  "es"
                        },
                 "EN":  {
                            "label":  "English",
                            "code":  "en"
                        },
                 "PT":  {
                            "label":  "Portuguese",
                            "code":  "pt"
                        }
             },
    "Menu":  {
                 "Menu_0":  {
                                "label":  "Home",
                                "url":  "/home",
                                "icono":  "fa-solid fa-house",
                                "visible":  true,
                                "code":  0
                            },
                 "Menu_1":  {
                                "label":  "Versions",
                                "url":  "/mantenimiento/versiones",
                                "icono":  "fa-solid fa-table-list",
                                "visible":  true,
                                "code":  1
                            },
                 "Menu_2":  {
                                "label":  "Versions Import",
                                "url":  "/gestion/importacion-versiones",
                                "icono":  "fa-solid fa-code-pull-request fa-flip-horizontal",
                                "visible":  true,
                                "code":  2
                            },
                 "Menu_3":  {
                                "label":  "Forecasts",
                                "url":  "/gestion/previsiones",
                                "icono":  "fa-solid fa-chart-line",
                                "visible":  true,
                                "code":  3
                            },
                 "Menu_4":  {
                                "label":  "Reports",
                                "url":  "",
                                "icono":  "",
                                "image":  "",
                                "visible":  false,
                                "code":  4
                            },
                 "Menu_5":  {
                                "label":  "Conditions Planning",
                                "url":  "/gestion/planificacion-condiciones",
                                "icono":  "fa-solid fa-solar-panel",
                                "visible":  true,
                                "code":  5
                            },
                 "Menu_7":  {
                                "label":  "iTracker",
                                "url":  "/reportes/itracker",
                                "icono":  "fa-solid fa-chart-column",
                                "visible":  false,
                                "code":  7
                            },
                 "Menu_8":  {
                                "label":  "Magnitude",
                                "url":  "/reportes/magnitude",
                                "icono":  "icon reporteMagnitude",
                                "visible":  false,
                                "code":  8
                            },
                 "Menu_9":  {
                                "label":  "Automatic Processes",
                                "url":  "",
                                "icono":  "",
                                "visible":  true,
                                "code":  9
                            },
                 "Menu_10":  {
                                 "label":  "GI to Billings",
                                 "url":  "/procesos-automaticos/gibillings",
                                 "icono":  "fa-solid fa-money-bill-transfer",
                                 "visible":  true,
                                 "code":  10
                             },
                 "Menu_11":  {
                                 "label":  "NV and NC from Agreements to Forecast",
                                 "url":  "/copiarinversiones",
                                 "icono":  "icon processos",
                                 "visible":  true,
                                 "code":  11
                             },
                 "Menu_12":  {
                                 "label":  "Indicators",
                                 "url":  "/mantenimiento/indicadores",
                                 "icono":  "fa-solid fa-list-ol",
                                 "visible":  true,
                                 "code":  12
                             },
                 "Menu_13":  {
                                 "label":  "Conditions Import",
                                 "url":  "/gestion/importacion-condiciones",
                                 "icono":  "fa-solid fa-file-import",
                                 "visible":  true,
                                 "code":  13
                             },
                 "Menu_14":  {
                                 "label":  "Overpremiums",
                                 "url":  "/gestion/sobreprimas",
                                 "icono":  "fa-solid fa-scale-balanced",
                                 "image":  "images/favoritos/sobreprimas.svg",
                                 "visible":  true,
                                 "code":  14
                             },
                 "Menu_15":  {
                                 "label":  "Maintenance",
                                 "url":  "",
                                 "icono":  "",
                                 "visible":  true,
                                 "code":  15
                             },
                 "Menu_16":  {
                                 "label":  "Importación Sobreprimas",
                                 "url":  "/gestion/importacion-sobreprimas",
                                 "icono":  "fa-solid fa-file-import",
                                 "visible":  true,
                                 "code":  16
                             },
                 "Menu_17":  {
                                 "label":  "Management",
                                 "url":  "",
                                 "icono":  "",
                                 "visible":  true,
                                 "code":  17
                             },
                 "Menu_18":  {
                                 "label":  "Adjustments",
                                 "url":  "/gestion/ajustes",
                                 "icono":  "fa-solid fa-gear",
                                 "visible":  true,
                                 "code":  18
                             },
                 "Menu_19":  {
                                 "label":  "Copy Investments",
                                 "url":  "/procesos-automaticos/copiar-inversiones",
                                 "icono":  "fa-solid fa-copy",
                                 "visible":  true,
                                 "code":  19
                             },
                 "Menu_20":  {
                                 "label":  "Administration",
                                 "url":  "",
                                 "icono":  "",
                                 "visible":  true,
                                 "code":  20
                             },
                 "Menu_21":  {
                                 "label":  "Sending Informative Messages",
                                 "url":  "/administracion/avisos",
                                 "icono":  "fa-solid fa-paper-plane",
                                 "visible":  true,
                                 "code":  21
                             },
                 "Menu_22":  {
                                 "label":  "Impersonation",
                                 "url":  "/administracion/impersonacion",
                                 "icono":  "fa-solid fa-users-gear",
                                 "visible":  true,
                                 "code":  22
                             },
                 "Menu_23":  {
                                 "label":  "Blocked Months",
                                 "url":  "/administracion/meses-bloqueados",
                                 "icono":  "fa-solid fa-calendar-days",
                                 "visible":  true,
                                 "code":  23
                             },
                 "Menu_24":  {
                                 "label":  "Configuration",
                                 "url":  "",
                                 "icono":  "",
                                 "visible":  true,
                                 "code":  24
                             },
                 "Menu_25":  {
                                 "label":  "Year for Journal",
                                 "url":  "/configuracion/anio-diario",
                                 "icono":  "fa-solid fa-clock",
                                 "visible":  true,
                                 "code":  25
                             },
                 "Menu_26":  {
                                 "label":  "Audits",
                                 "url":  "/admin/auditorias",
                                 "icono":  "fa-solid fa-magnifying-glass-chart",
                                 "visible":  true,
                                 "code":  26
                             }
             },
    "Pages":  {
                  "ITracker":  {
                                   "TypeVersionSource":  {
                                                             "Channels":  {
                                                                              "label":  "Channels",
                                                                              "code":  1
                                                                          },
                                                             "Publishers":  {
                                                                                "label":  "Publishers",
                                                                                "code":  2
                                                                            }
                                                         }
                               },
                  "Login":  {
                                "CerrarSesion":  {
                                                     "label":  "Close sesion"
                                                 }
                            },
                  "Editoriales":  {

                                  },
                  "Versiones":  {
                                    "Indicadores":  {
                                                        "label":  "Indicators"
                                                    },
                                    "Tipo":  {
                                                 "label":  "Type"
                                             },
                                    "Versiones":  {
                                                      "label":  "Versions"
                                                  },
                                    "Version":  {
                                                    "label":  "Version"
                                                },
                                    "LeyendasIndicadores":  {
                                                                "label":  "Indicators Legends"
                                                            },
                                    "NombreIndicador":  {
                                                            "label":  "Indicator Name"
                                                        },
                                    "Message_VersionDescriptionError":  {
                                                                            "label":  "Version description {0} matches another version\u0027s description. The description cannot be duplicated among versions"
                                                                        },
                                    "HayDatosRelacionadosConLaVersion":  {
                                                                             "label":  "The Version cannot be deleted because it has related data"
                                                                         },
                                    "TipoVersion":  {
                                                        "User":  {
                                                                     "label":  "User",
                                                                     "code":  1
                                                                 },
                                                        "Monthly":  {
                                                                        "label":  "Monthly",
                                                                        "code":  2
                                                                    },
                                                        "Backup":  {
                                                                       "label":  "Backup",
                                                                       "code":  3
                                                                   }
                                                    }
                                },
                  "GestionVersiones":  {
                                           "ToolTip":  {
                                                           "label":  "Allows transferring investment data between versions, filtering by client groups or other fields of the new data model. It is necessary to select a Source Version-Year and a Target Version-Year"
                                                       },
                                           "TypeVersionSource":  {
                                                                     "Presupuestos":  {
                                                                                          "label":  "Budgets",
                                                                                          "code":  1
                                                                                      },
                                                                     "Inges":  {
                                                                                   "label":  "Actual",
                                                                                   "code":  2
                                                                               },
                                                                     "Set0":  {
                                                                                  "label":  "Set to 0",
                                                                                  "code":  3
                                                                              }
                                                                 }
                                       },
                  "Indicadores":  {
                                      "ToolTip":  {
                                                      "label":  "Maintenance of status Indicators for Versions"
                                                  },
                                      "VersionUnica":  {
                                                           "label":  "Unique Version"
                                                       },
                                      "ListaIndicadores":  {
                                                               "label":  "Indicators List"
                                                           },
                                      "Mostrar":  {
                                                      "label":  "Show"
                                                  },
                                      "LanguageDataIncompleted":  {
                                                                      "label":  "There are mandatory language fields not filled"
                                                                  },
                                      "Grabar":  {
                                                     "label":  "Save"
                                                 },
                                      "Actualizar":  {
                                                         "label":  "Refresh"
                                                     }
                                  },

                  "Index":  {
                                "Hola":  {
                                             "label":  "Hello"
                                         },
                                "Bienvenida":  {
                                                   "label":  "Welcome to the Budgets application"
                                               }
                            },
                  "SelectorIdioma":  {

                                     },
                  "PlanificacionCondiciones":  {
                                                   "Alcance":  {
                                                                   "label":  "Scope"
                                                               },
                                                   "Disciplina":  {
                                                                      "label":  "Discipline"
                                                                  },
                                                   "Diversified":  {
                                                                       "label":  "Diversified"
                                                                   },
                                                   "Excepciones":  {
                                                                       "label":  "Exceptions"
                                                                   },
                                                   "ExcepcionesMedio":  {
                                                                            "label":  "Media Exceptions:"
                                                                        },
                                                   "Objetivo":  {
                                                                    "label":  "Objective"
                                                                },
                                                   "TipoCompra":  {
                                                                      "label":  "Purchase Type"
                                                                  },
                                                   "TipoDisciplina":  {
                                                                          "label":  "Nature"
                                                                      },
                                                   "DisciplinaGrupo":  {
                                                                           "label":  "Group Discipline"
                                                                       },
                                                   "ToolTip":  {
                                                                   "label":  "Allows entering the agency service and the selected group\u0027s rebate."
                                                               },
                                                   "Jerarquia":  {
                                                                     "label":  "Hierarchy"
                                                                 },
                                                   "Condiciones":  {
                                                                       "label":  "Conditions Planning"
                                                                   },
                                                   "CondicionesAcuerdos":  {
                                                                               "label":  "Agreement Conditions Planning"
                                                                           },
                                                   "CondicionesCodigo":  {
                                                                             "Code":  0
                                                                         },
                                                   "CondicionesAcuerdosCodigo":  {
                                                                                     "Code":  1
                                                                                 },
                                                   "Vigencias":  {
                                                                     "label":  "Validities"
                                                                 },
                                                   "ToolTipSagTpc":  {
                                                                         "label":  "Agency Service Percentage"
                                                                     },
                                                   "ToolTipManpowerTpc":  {
                                                                              "label":  "Manpower Percentage"
                                                                          },
                                                   "ToolTipDevolucionTpc":  {
                                                                                "label":  "Rebate Percentage"
                                                                            },
                                                   "SagTpc":  {
                                                                  "label":  "% SAG"
                                                              },
                                                   "ManpowerTpc":  {
                                                                       "label":  "% MNP"
                                                                   },
                                                   "NumExcepciones":  {
                                                                          "label":  "No. Exceptions"
                                                                      },
                                                   "NetoVenta":  {
                                                                     "label":  "Net Sale"
                                                                 },
                                                   "Sobreprima":  {
                                                                      "label":  "Overpremium"
                                                                  },
                                                   "DevolucionTpc":  {
                                                                         "label":  "% DEV"
                                                                     },
                                                   "BCDevolucion":  {
                                                                        "label":  "Rebate Base"
                                                                    },
                                                   "NuevaVigencia":  {
                                                                         "label":  "New Validity"
                                                                     },
                                                   "EditarVigencia":  {
                                                                          "label":  "Edit Validity"
                                                                      },
                                                   "VigenciaSeleccion":  {
                                                                              "label":  "Please select a validity period"
                                                                          },
                                                   "FiltroPorMedio":  {
                                                                          "label":  "Filter by Media"
                                                                      },
                                                   "FiltroExcepciones":  {
                                                                             "label":  "Exceptions Filter"
                                                                         },
                                                   "Mensajes":  {
                                                                    "VigenciasSolapadas":  {
                                                                                               "label":  "The months coincide with another validity, please review."
                                                                                           },
                                                                    "VigenciaConCondiciones":  {
                                                                                                   "label":  "The selected Validity has associated Conditions that will be deleted. Do you wish to continue?"
                                                                                               },
                                                                    "VigenciaModificada":  {
                                                                                               "label":  "Validity modified"
                                                                                           },
                                                                    "VigenciaSinMeses":  {
                                                                                             "label":  "Please select the months for the validity"
                                                                                         },
                                                                    "VigenciaValidacion":  {
                                                                                               "label":  "The start month cannot be greater than the end month"
                                                                                           },
                                                                    "PctDevCondicionSinBC":  {
                                                                                                 "label":  "Please, when entering a %Rebate in conditions, you must select a Calculation Base"
                                                                                             },
                                                                    "PctExcepcionSinPctSAGCondicion":  {
                                                                                                           "label":  "Please, when entering a % in exceptions, you must have % in the condition for the same media"
                                                                                                       },
                                                                    "PctExcepcionSinPctManPowerCondicion":  {
                                                                                                                "label":  "Please, when entering a % in exceptions, you must have % in the condition for the same media"
                                                                                                            },
                                                                    "PctExcepcionSinPctDEVCondicion":  {
                                                                                                           "label":  "Please, when entering a % in exceptions, you must have % in the condition for the same media"
                                                                                                       },
                                                                    "ExcepcionesSinCondiciones":  {
                                                                                                      "label":  "Exceptions cannot be created by media without having conditions for that media"
                                                                                                  },
                                                                    "MedioExcepcionConDatosDuplicados":  {
                                                                                                             "label":  "Media {0} has duplicated data in exceptions."
                                                                                                         },
                                                                    "PctEnTodasExcepciones":  {
                                                                                                  "label":  "All exceptions must have at least one percentage."
                                                                                              },
                                                                    "ConceptoNMDEnTodasExcepciones":  {
                                                                                                          "label":  "All exceptions must have at least one NMD Concept selected"
                                                                                                      },
                                                                    "ExcepcionesConCondicionesEnMedio":  {
                                                                                                             "label":  "All exceptions must have conditions for their media"
                                                                                                         },
                                                                    "PctDevExcepcionSinBD":  {
                                                                                                 "label":  "Please, when entering a %Rebate in exceptions, you must select a BC indicator"
                                                                                             },
                                                                    "AlFiltrarExcepcionesConCambios":  {
                                                                                                           "label":  "When filtering exceptions with changes"
                                                                                                       },
                                                                    "CancelarCambiosCondiciones":  {
                                                                                                       "label":  "There are unsaved changes in Conditions. Do you wish to continue and lose these changes?"
                                                                                                   },
                                                                    "CancelarCambiosExcepciones":  {
                                                                                                       "label":  "There are unsaved changes in Exceptions. Do you wish to continue and lose these changes?"
                                                                                                   },
                                                                    "BCCondicionSinPctDevolucion":  {
                                                                                                        "label":  "Please, when entering a Calculation Base in conditions, you must enter a Percentage."
                                                                                                    },
                                                                    "VigenciaAñadida":  {
                                                                                            "label":  "Validity added"
                                                                                        }
                                                                }
                                               },
                 
                  "Sobreprimas":  {
                                      "ToolTip":  {
                                                      "label":  "Allows loading overpremiums in Budgets or importing existing ones from MMS."
                                                  },
                                      "Sobreprimas":  {
                                                          "label":  "Overpremiums"
                                                      },
                                      "TypeConcept":  {
                                                          "Default":  {
                                                                          "label":  "Overpremium",
                                                                          "code":  1
                                                                      },
                                                          "SLA":  {
                                                                      "label":  "SLA Overpremium",
                                                                      "code":  2
                                                                  },
                                                          "HVP":  {
                                                                      "label":  "HVP Overpremium",
                                                                      "code":  3
                                                                  }
                                                      }
                                  },
                  "Magnitude":  {

                                },
                  "CopiarInversiones":  {

                                        },
                  "Avisos":  {
                                 "Titulo":  {
                                                "label":  "General Notice"
                                            },
                                 "ToolTip":  {
                                                 "Label":  "Utility to send notifications that all users currently connected to the application will see"
                                             },
                                 "Mensaje":  {
                                                 "Label":  "Notice Message:"
                                             },
                                 "TipoAviso":  {
                                                   "Label":  "Notice Type:"
                                               }
                             },
                  "Impersonation":  {
                                        "ToolTip":  {
                                                        "label":  "Access to the application impersonating another user"
                                                    },
                                        "UserName":  {
                                                         "label":  "Username"
                                                     },
                                        "Password":  {
                                                         "label":  "User Password"
                                                     },
                                        "Description":  {
                                                            "label":  "Enter the username and password to impersonate"
                                                        },
                                        "RellenarDatosUsuario":  {
                                                                     "label":  "Fill username and password"
                                                                 },
                                        "Error":  {
                                                      "label":  "An error occurred and the process was not completed"
                                                  },
                                        "UsuarioNoAutorizado":  {
                                                                    "label":  "The user does not have permission to access the application"
                                                                },
                                        "UsuarioImpersonadoIgual":  {
                                                                        "label":  "The user to impersonate must be different from the authenticated user"
                                                                    }
                                    },
                  "ModalInactividad":  {
                                           "Titulo":  {
                                                          "label":  "Inactivity Notice"
                                                      },
                                           "CuentaAtras":  {
                                                               "label":  "Returns to Home page in:"
                                                           }
                                       },
                  "MesesBloqueados":  {
                                          "ToolTip":  {
                                                          "label":  "Allows selecting months in a selected year to block them)"
                                                      },
                                          "MesesBloqueados":  {
                                                                  "label":  "Blocked Months"
                                                              }
                                      },
                  "Auditorias":  {
                                     "ToolTip":  {
                                                     "label":  "System audits"
                                                 },
                                     "TipoAuditoria":  {
                                                           "label":  "Audit type"
                                                       },
                                     "FechaInicio":  {
                                                         "label":  "Start date"
                                                     },
                                     "FechaFin":  {
                                                      "label":  "End date"
                                                  },
                                     "Usuario":  {
                                                     "label":  "User"
                                                 },
                                     "CamposObligatorios":  {
                                                                "label":  "You must select the audit type"
                                                            },
                                     "Pagina":  {
                                                    "label":  "Page"
                                                }
                                 },
                  "AnioDiario":  {
                                     "ToolTip":  {
                                                     "label":  "Allows selecting year for the Budgets Journal"
                                                 }
                                 },
                  "ImportacionCondiciones":  {
                                                 "ToolTip":  {
                                                                 "label":  "Allows importing MMS conditions filtering by given parameters."
                                                             },
                                                 "ImportarCondicionesMMS":  {
                                                                                "label":  "Import MMS conditions"
                                                                            },
                                                 "LinkCondiciones":  {
                                                                         "label":  "View imported Conditions"
                                                                     },
                                                 "LinkCondicionesHelp":  {
                                                                             "label":  "Navigate to the Conditions page filtering by performed import"
                                                                         }
                                             },
                  "ImportacionSobreprimas":  {

                                             }
              },
    "Common":  {
                   "AppName":  {
                                   "const":  "Presupuestos"
                               },
                   "Http404":  {
                                   "label":  "Page Not Found"
                               },
                   "Http403":  {
                                   "label":  "Access Forbidden"
                               },
                   "Http400":  {
                                   "label":  "Bad Request"
                               },
                   "Http500":  {
                                   "label":  "Internal Server Error"
                               },
                   "HttpError":  {
                                     "label":  "Unhandled Internal Error"
                                 },
                   "Aceptar":  {
                                   "label":  "Accept"
                               },
                   "AgrupacionComercial":  {
                                               "label":  "Commercial Grouping"
                                           },
                   "Anio":  {
                                "label":  "Year"
                            },
                   "BackToHome":  {
                                      "label":  "Go to Home"
                                  },
                   "BitAnd":  {
                                  "label":  "BitAnd"
                              },
                   "Buscar":  {
                                  "label":  "Search"
                              },
                   "Cancelar":  {
                                    "label":  "Cancel"
                                },
                   "Loading":  {
                                   "label":  "Loading"
                               },
                   "Codigo":  {
                                  "label":  "Code"
                              },
                   "DatosGrabados":  {
                                         "label":  "Data saved successfully"
                                     },
                   "Detalle":  {
                                   "label":  "Detail"
                               },
                   "Descripcion":  {
                                       "label":  "Description"
                                   },
                   "DescripcionAbreviada":  {
                                                "label":  "Abbreviated Description"
                                            },
                   "DesmarcarFavorito":  {
                                             "label":  "Unmark favorite"
                                         },
                   "Edit":  {
                                "label":  "Edit"
                            },
                   "EditarRegistro":  {
                                          "label":  "Edit record"
                                      },
                   "Editorial":  {
                                     "label":  "Publisher"
                                 },
                   "EliminarRegistro":  {
                                            "label":  "Delete record"
                                        },
                   "EscribaTextoBusqueda":  {
                                                "label":  "Enter search text..."
                                            },
                   "FiltroQuitar":  {
                                        "label":  "Remove Filter"
                                    },
                   "Filtros":  {
                                   "label":  "Filters"
                               },
                   "GrupoClientes":  {
                                         "label":  "Client Group"
                                     },
                   "Idioma":  {
                                  "label":  "Language"
                              },
                   "Leyenda":  {
                                   "label":  "Legend"
                               },
                   "Limpiar":  {
                                   "label":  "Clear"
                               },
                   "MarcarFavorito":  {
                                          "label":  "Mark as favorite"
                                      },
                   "Medio":  {
                                 "label":  "Media"
                             },
                   "Medios":  {
                                  "label":  "Media"
                              },
                   "Mes":  {
                               "label":  "Month"
                           },
                   "MesDesde":  {
                                    "label":  "Start Month"
                                },
                   "MesHasta":  {
                                    "label":  "End Month"
                                },
                   "No":  {
                              "label":  "No"
                          },
                   "Network":  {
                                   "label":  "Network"
                               },
                   "Nuevo":  {
                                 "label":  "New"
                             },
                   "Orden":  {
                                 "label":  "Order"
                             },
                   "Parametros":  {
                                      "label":  "Parameters"
                                  },
                   "Save":  {
                                "label":  "Save"
                            },
                   "Si":  {
                              "label":  "Yes"
                          },
                   "Todos":  {
                                 "label":  "All"
                             },
                   "Todo":  {
                                "label":  "All"
                            },
                   "Porcentaje":  {
                                      "label":  "Percentage"
                                  },
                   "Prueba":  {
                                  "label":  "Test"
                              },
                   "UnauthorizedUser":{
                                            "label":  "Unauthorized User"
                                        },
                   "Version":  {
                                   "label":  "Version"
                               },
                   "Messages":  {
                                    "UndefinedError":  {
                                                           "label":  "Undefined Error"
                                                       }
                                },
      "LogActions": {
        "DatosGuardadosCorrectamente": {
          "label": "Data saved successfully"
        },
        "ErrorGuardandoDatos": {
          "label": "Error saving data"
        },
        "AccesoPagina": {
          "label": "Page access"
        },
        "DatosEliminadosCorrectamente": {
          "label": "Data deleted successfully"
        },
        "ErrorEliminandoDatos": {
          "label": "Error deleting data"
        }
      }
               },
    "Botones":  {
                    "Añadir":  {
                                   "label":  "Add"
                               },
                    "Cancelar":  {
                                     "label":  "Cancel"
                                 },
                    "Eliminar":  {
                                     "label":  "Delete"
                                 },
                    "Grabar":  {
                                   "label":  "Save"
                               },
                    "Modificar":  {
                                      "label":  "Modify"
                                  },
                    "Enviar":  {
                                   "label":  "Send"
                               },
                    "Cerrar":  {
                                   "label":  "Close"
                               }
                },
    "Mensajes":  {
                     "Cancelar":  {
                                      "label":  "There are unsaved changes. Do you wish to continue and lose these changes?"
                                  },
                     "CampoMayorQueCero":  {
                                               "label":  "Field {0} must be greater than 0"
                                           },
                     "CamposObligatorios":  {
                                                "label":  "Please fill all fields indicated as mandatory."
                                            },
                     "ConfirmacionEliminar":  {
                                                  "label":  "You are going to delete the selected record. Do you wish to continue?"
                                              },
                     "IdiomasDuplicados":  {
                                               "label":  "Duplicate Languages exist."
                                           },
                     "SinModificaciones":  {
                                               "label":  "No modifications"
                                           },
                     "RegistrosNoEncontrados":  {
                                                    "label":  "No records found with the indicated search parameters."
                                                },
                     "RegistroEliminado":  {
                                               "label":  "Record deleted"
                                           },
                     "RegistroGrabado":  {
                                             "label":  "Record saved"
                                         },
                     "ErrorGeneral":  {
                                          "label":  "The process was not completed successfully. Please consult support."
                                      },
                     "ErrorAlGrabar":  {
                                           "label":  "The process was not completed successfully. Try saving the record again and if the error persists, contact support."
                                       },
                     "ValidarBitAnd":  {
                                           "label":  "The value entered for the BitAnd field does not have a single 1 in binary ({0})."
                                       },
                     "ValorCampoRepetido":  {
                                                "label":  "Value {1} of field {0} already exists."
                                            },
                     "AvisoAntesCancelar":  {
                                                "label":  "There are unsaved changes. Do you wish to continue and lose these changes?"
                                            },
                     "IndicadorUnico":  {
                                            "label":  "Indicator {0} can only be selected for one version."
                                        },
                     "SinCambios":  {
                                        "Label":  "No changes to save. "
                                    },
                     "MandatoryField":  {
                                            "Label":  "Mandatory field"
                                        },
                     "LongitudCaracteres":  {
                                                "Label":  "Please review the entered information, it exceeds the character limit accepted in the field "
                                            },
                     "ErrorDelete":  {
                                         "label":  "A problem occurred and the record was not deleted. Please consult Support"
                                     },
                     "CampoVersionObligatorio":  {
                                                     "label":  "Version Description is a mandatory field"
                                                 },
                     "PermisosInsuficientes":  {
                                                   "label":  "You do not have the necessary permissions to perform the indicated operation"
                                               },
                     "SobreprimaDuplicated":  {
                                                  "Label":  "Duplicate Overpremium. Review data "
                                              },
                     "IndicadorCerradaConIndicadorReal":  {
                                                              "label":  "If the version has the {0} indicator active, the {1} indicator must be active."
                                                          },
                     "AvisoCambiosPendientes":  {
                                                    "Label":  "There are unsaved changes. Do you wish to continue and lose these changes?"
                                                },
                     "ErrorAbriendoPantalla":  {
                                                   "label":  "Error initializing the screen. Please consult support."
                                               },
                     "ImportacionCondicionesFinalizada":  {
                                                              "label":  "Conditions import successful."
                                                          },
                     "ErrorDespuesDeGrabar":  {
                                                  "label":  "Process completed with errors in the on-screen data update. Consult support"
                                              },
                     "AvisoImportarCondiciones":  {
                                                      "label":  "You are about to import Conditions with the specified parameters. The current ones will be deleted. Do you want to continue?"
                                                  },
                     "LoggingError":  {
                                          "label":  "⚠️ The error could not be recorded in the logging system. The support team has been notified."
                                      },
                     "DatabaseWarning":  {
                                             "label":  "Database manager warning"
                                         }
                 },
    "Meses":  {

              },
    "MensajeErrorBD":  {

                       }
}